setup.py
compounding_interest/__init__.py
compounding_interest/compounding_interest.py
compounding_interest.egg-info/PKG-INFO
compounding_interest.egg-info/SOURCES.txt
compounding_interest.egg-info/dependency_links.txt
compounding_interest.egg-info/not-zip-safe
compounding_interest.egg-info/top_level.txt