Metadata-Version: 2.1
Name: compounding-interest
Version: 0.1
Summary: For calculating compound interest
Author: B A L A N
